tidal_wave/__init__.py
tidal_wave/__main__.py
tidal_wave/album.py
tidal_wave/artist.py
tidal_wave/dash.py
tidal_wave/hls.py
tidal_wave/login.py
tidal_wave/main.py
tidal_wave/media.py
tidal_wave/mix.py
tidal_wave/models.py
tidal_wave/oauth.py
tidal_wave/playlist.py
tidal_wave/requesting.py
tidal_wave/track.py
tidal_wave/utils.py
tidal_wave/video.py
tidal_wave-2026.3.2.dist-info/LICENSE
tidal_wave-2026.3.2.dist-info/METADATA
tidal_wave-2026.3.2.dist-info/WHEEL
tidal_wave-2026.3.2.dist-info/entry_points.txt
tidal_wave-2026.3.2.dist-info/top_level.txt
tidal_wave-2026.3.2.dist-info/RECORD
