Metadata-Version: 2.1
Name: tidal-wave
Version: 2026.3.2
Summary: A tool to wave at the TIDAL music service.
Author-email: colinho <pypi@colin.technology>
Maintainer-email: colinho <pypi@colin.technology>
License: Apache License
Project-URL: Homepage, https://github.com/ebb-earl-co/tidal-wave
Classifier: Intended Audience :: End Users/Desktop
Classifier: Programming Language :: Python :: 3
Classifier: Programming Language :: Python :: 3.8
Classifier: Programming Language :: Python :: 3.9
Classifier: Programming Language :: Python :: 3.10
Classifier: Programming Language :: Python :: 3.11
Classifier: Programming Language :: Python :: 3.12
Classifier: Operating System :: OS Independent
Classifier: Topic :: Multimedia :: Sound/Audio
Classifier: Topic :: Multimedia :: Video
Requires-Python: >=3.8
License-File: LICENSE
Requires-Dist: backoff ==2.2.1
Requires-Dist: dataclass-wizard ==0.22.3
Requires-Dist: ffmpeg-python ==0.2.0
Requires-Dist: mutagen ==1.47.0
Requires-Dist: m3u8 ==4.0.0
Requires-Dist: platformdirs ==4.2.0
Requires-Dist: pycryptodome ==3.20.0
Requires-Dist: requests[socks] ==2.31.0
Requires-Dist: typer ==0.9.0
Provides-Extra: all
Requires-Dist: typer[all] ==0.9.0 ; extra == 'all'
